retrolib/PixelArt.py
retrolib/__init__.py
retrolib-0.3.2.dist-info/LICENSE
retrolib-0.3.2.dist-info/LICENSE_FR
retrolib-0.3.2.dist-info/METADATA
retrolib-0.3.2.dist-info/WHEEL
retrolib-0.3.2.dist-info/top_level.txt
retrolib-0.3.2.dist-info/RECORD
