Metadata-Version: 2.1
Name: retrolib
Version: 0.3.2
Summary: Une bibliothèque avec des trucs retro. A library with retro stuff.
Author: Léonor Leclerc
Author-email: leo-nor7777@outlook.com
Classifier: Programming Language :: Python :: 3
Classifier: License :: OSI Approved :: MIT License
Classifier: Operating System :: OS Independent
Requires-Python: >=3.4
License-File: LICENSE
License-File: LICENSE_FR
Requires-Dist: Pillow
